{"behaviors":["Spin"],"defaultCamera":3,"entities":[{"components":{"Mesh":{"meshId":"builtin:cube"},"Transform":{"rotation":[1.0,0.0,0.0,0.0],"scale":[8.0,8.0,0.20000000298023224],"translation":[0.0,0.0,0.0]},"Visual":{"materialId":"builtin:default"}},"id":0,"name":"Ground","parent":null},{"components":{"Mesh":{"meshId":"builtin:cube"},"Spin":{"angularVelocity":[0.0,0.0,3.0]},"Transform":{"rotation":[0.9848077297210693,0.1736481785774231,0.0,0.0],"scale":[0.5,0.5,0.5],"translation":[0.0,0.0,1.2000000476837158]},"Visual":{"materialId":"builtin:default"}},"id":1,"name":"Dreidel","parent":null},{"components":{"DirectionalLight":{"castsShadows":true,"color":[1.0,1.0,1.0],"direction":[-1.0,-1.0,-1.0],"intensity":1.0}},"id":2,"name":"DirectionalLight","parent":null},{"components":{"Camera":{"aspect":0.0,"domain":1,"farPlane":100.0,"fovY":0.7853981852531433,"nearPlane":0.10000000149011612},"Transform":{"rotation":[1.0,0.0,0.0,0.0],"scale":[1.0,1.0,1.0],"translation":[5.0,5.0,3.0]}},"id":3,"name":"Camera","parent":null}],"formatVersion":1,"name":""}